LICENSE
README.rst
setup.py
google/ads/googleads/__init__.py
google/ads/googleads/client.py
google/ads/googleads/config.py
google/ads/googleads/errors.py
google/ads/googleads/oauth2.py
google/ads/googleads/util.py
google/ads/googleads/interceptors/__init__.py
google/ads/googleads/interceptors/exception_interceptor.py
google/ads/googleads/interceptors/helpers.py
google/ads/googleads/interceptors/interceptor.py
google/ads/googleads/interceptors/logging_interceptor.py
google/ads/googleads/interceptors/metadata_interceptor.py
google/ads/googleads/interceptors/response_wrappers.py
google/ads/googleads/v14/__init__.py
google/ads/googleads/v14/gapic_version.py
google/ads/googleads/v14/common/__init__.py
google/ads/googleads/v14/common/gapic_version.py
google/ads/googleads/v14/common/services/__init__.py
google/ads/googleads/v14/common/types/__init__.py
google/ads/googleads/v14/common/types/ad_asset.py
google/ads/googleads/v14/common/types/ad_type_infos.py
google/ads/googleads/v14/common/types/asset_policy.py
google/ads/googleads/v14/common/types/asset_set_types.py
google/ads/googleads/v14/common/types/asset_types.py
google/ads/googleads/v14/common/types/asset_usage.py
google/ads/googleads/v14/common/types/audiences.py
google/ads/googleads/v14/common/types/bidding.py
google/ads/googleads/v14/common/types/click_location.py
google/ads/googleads/v14/common/types/criteria.py
google/ads/googleads/v14/common/types/criterion_category_availability.py
google/ads/googleads/v14/common/types/custom_parameter.py
google/ads/googleads/v14/common/types/customizer_value.py
google/ads/googleads/v14/common/types/dates.py
google/ads/googleads/v14/common/types/extensions.py
google/ads/googleads/v14/common/types/feed_common.py
google/ads/googleads/v14/common/types/feed_item_set_filter_type_infos.py
google/ads/googleads/v14/common/types/final_app_url.py
google/ads/googleads/v14/common/types/frequency_cap.py
google/ads/googleads/v14/common/types/keyword_plan_common.py
google_ads.egg-info/PKG-INFO
google_ads.egg-info/SOURCES.txt
google_ads.egg-info/dependency_links.txt
google_ads.egg-info/namespace_packages.txt
google_ads.egg-info/not-zip-safe
google_ads.egg-info/requires.txt
google_ads.egg-info/top_level.txt