Metadata-Version: 2.1
Name: google-ads
Version: 23.0.0
Summary: Client library for the Google Ads API
Home-page: https://github.com/googleads/google-ads-python
Author: Google LLC
Author-email: googleapis-packages@google.com
License: Apache 2.0
Classifier: Intended Audience :: Developers
Classifier: Development Status :: 5 - Production/Stable
Classifier: Intended Audience :: Developers
Classifier: License :: OSI Approved :: Apache Software License
Classifier: Programming Language :: Python
Classifier: Programming Language :: Python :: 3
Classifier: Programming Language :: Python :: 3.8
Classifier: Programming Language :: Python :: 3.9
Classifier: Programming Language :: Python :: 3.10
Classifier: Programming Language :: Python :: 3.11
Classifier: Programming Language :: Python :: 3.12
Requires-Python: >=3.8, <3.13
License-File: LICENSE
Requires-Dist: google-auth-oauthlib<2.0.0,>=0.3.0
Requires-Dist: google-api-core<=3.0.0,>=2.13.0
Requires-Dist: googleapis-common-protos<2.0.0,>=1.56.3
Requires-Dist: grpcio<2.0.0,>=1.59.0
Requires-Dist: grpcio-status<2.0.0,>=1.59.0
Requires-Dist: proto-plus<2.0.0,>=1.22.3
Requires-Dist: PyYAML<7.0,>=5.1
Requires-Dist: protobuf<5.0.0,>=4.25.0
Provides-Extra: tests
Requires-Dist: nox<2022.6,>=2020.12.31; extra == "tests"
